setup.py
scopus_spider/__init__.py
scopus_spider.egg-info/PKG-INFO
scopus_spider.egg-info/SOURCES.txt
scopus_spider.egg-info/dependency_links.txt
scopus_spider.egg-info/not-zip-safe
scopus_spider.egg-info/top_level.txt